{
  "display": {
    "background": "marvel:textures/marvel_advancement_background.png",
    "icon": {
      "item": "marvel:captain_americas_shield_red"
    },
    "title": {
      "translate": "advancements.marvel_advancement_root.title"
    },
    "description": {
      "translate": "advancements.marvel_advancement_root.descr"
    },
    "frame": "task",
    "show_toast": false,
    "announce_to_chat": false,
    "hidden": false
  },
  "criteria": {
    "marvel_advancement_root": {
      "trigger": "minecraft:inventory_changed",
      "conditions": {
        "items": [
          {
            "items": [
              "minecraft:oak_log"
            ],
            "count": {
              "min": 1,
              "max": 64
            }
          }
        ]
      }
    }
  },
  "rewards": {
    "experience": 1
  }
}