{
  "item.vibranium_shield.throw": {
    "subtitle": "subtitles.item.vibranium_shield.throw",
    "sounds": [
      "marvel:item/vibranium_shield/throw"
    ]
  },
  "item.vibranium_shield.hit": {
    "subtitle": "subtitles.item.vibranium_shield.hit",
    "sounds": [
      "marvel:item/vibranium_shield/hit"
    ]
  },
  "suit.kinetic_black_panther.suit_up": {
    "subtitle": "subtitles.suit.kinetic_black_panther.suit_up",
    "sounds": [
      "marvel:suit/kinetic_black_panther/suit_up"
    ]
  },
  "suit.kinetic_black_panther.suit_down": {
    "subtitle": "subtitles.suit.kinetic_black_panther.suit_down",
    "sounds": [
      "marvel:suit/kinetic_black_panther/suit_down"
    ]
  },
  "suit.kinetic_black_panther.helmet_up": {
    "subtitle": "subtitles.suit.kinetic_black_panther.helmet_up",
    "sounds": [
      "marvel:suit/kinetic_black_panther/helmet"
    ]
  },
  "suit.kinetic_black_panther.helmet_down": {
    "subtitle": "subtitles.suit.kinetic_black_panther.helmet_down",
    "sounds": [
      "marvel:suit/kinetic_black_panther/helmet"
    ]
  },
  "suit.wolverine.claws_out": {
    "subtitle": "subtitles.suit.wolverine.claws_out",
    "sounds": [
      "marvel:suit/wolverine/claws_out"
    ]
  },
  "suit.wolverine.claws_in": {
    "subtitle": "subtitles.suit.wolverine.claws_in",
    "sounds": [
      "marvel:suit/wolverine/claws_in"
    ]
  },
  "suit.cyclops.optic_blast": {
    "subtitle": "subtitles.suit.cyclops.optic_blast",
    "sounds": [
      "marvel:suit/cyclops/optic_blast"
    ]
  },
  "suit.cyclops.optic_blast_big": {
    "subtitle": "subtitles.suit.cyclops.optic_blast_big",
    "sounds": [
      "marvel:suit/cyclops/optic_blast_big"
    ]
  },
  "suit.cyclops.optic_blast_explosion": {
    "subtitle": "subtitles.entity.generic.explode",
    "sounds": [
      {
        "name": "minecraft:random/explode1",
        "volume": 0.4
      },
      {
        "name": "minecraft:random/explode2",
        "volume": 0.4
      },
      {
        "name": "minecraft:random/explode3",
        "volume": 0.4
      },
      {
        "name": "minecraft:random/explode4",
        "volume": 0.4
      }
    ]
  },
  "suit.ant_man.helmet_open": {
    "subtitle": "subtitles.suit.ant_man.helmet_open",
    "sounds": [
      "marvel:suit/ant_man/helmet_open"
    ]
  },
  "suit.ant_man.helmet_close": {
    "subtitle": "subtitles.suit.ant_man.helmet_close",
    "sounds": [
      "marvel:suit/ant_man/helmet_close"
    ]
  },
  "suit.ant_man.shrink": {
    "subtitle": "subtitles.suit.ant_man.shrink",
    "sounds": [
      "marvel:suit/ant_man/shrink"
    ]
  },
  "suit.ant_man.grow": {
    "subtitle": "subtitles.suit.ant_man.grow",
    "sounds": [
      "marvel:suit/ant_man/grow"
    ]
  }
}