{
  "required": true,
  "minVersion": "0.8",
  "package": "net.tintankgames.marvel.mixin",
  "compatibilityLevel": "JAVA_21",
  "mixins": [
    "BlockBehaviourMixin",
    "EnchantmentHelperMixin",
    "EntityMixin",
    "FallingBlockEntityMixin",
    "IMobEffectExtensionMixin",
    "LivingEntityMixin",
    "PlayerMixin",
    "ServerLevelMixin",
    "VanillaRegistriesMixin",
    "VanillaRegistriesMixin$DamageTypesMixin",
    "VanillaRegistriesMixin$FeatureUtilsMixin",
    "VanillaRegistriesMixin$PlacementUtilsMixin",
    "WebBlockMixin"
  ],
  "client": [
    "ArmorStandRendererMixin",
    "BlockEntityWithoutLevelRendererMixin",
    "CameraMixin",
    "CapeLayerMixin",
    "GameRendererMixin",
    "HumanoidArmorLayerMixin",
    "HumanoidModelMixin",
    "ItemInHandLayerMixin",
    "ItemInHandRendererMixin",
    "ItemTransformsMixin",
    "LevelRendererMixin",
    "LivingEntityRendererMixin",
    "MinecraftMixin",
    "PlayerModelMixin",
    "PlayerRendererMixin"
  ],
  "injectors": {
    "defaultRequire": 1
  }
}
