{
  "_fv": 24,
  "_type": "food",
  "definition": {
    "renderType": 0,
    "texture": "super_soldier_serum",
    "customModelName": "Normal",
    "name": "Super Soldier Serum",
    "rarity": "COMMON",
    "specialInfo": [],
    "creativeTab": {
      "value": "CUSTOM:MarvelItems"
    },
    "stackSize": 1,
    "nutritionalValue": 0,
    "saturation": 0.0,
    "eatingSpeed": 32,
    "resultItem": {
      "value": "Items.GLASS_BOTTLE"
    },
    "forDogs": false,
    "isAlwaysEdible": true,
    "animation": "drink",
    "hasGlow": false,
    "onEaten": {
      "name": "SuperSoldierSerumTaken"
    }
  }
}